hsys/__init__.py
hsys/gpu/__init__.py
hsys-0.1.0.dist-info/licenses/LICENSE
hsys-0.1.0.dist-info/METADATA
hsys-0.1.0.dist-info/WHEEL
hsys-0.1.0.dist-info/entry_points.txt
hsys-0.1.0.dist-info/top_level.txt
hsys-0.1.0.dist-info/RECORD
