Metadata-Version: 2.4
Name: hsys
Version: 0.1.0
Summary: System Information for Herlegon tools
Author: Jep Etau
Project-URL: Homepage, https://github.com/herlegon/hsys
Keywords: hardware information,system info
Classifier: Development Status :: 3 - Alpha
Classifier: Intended Audience :: Developers
Classifier: Operating System :: OS Independent
Classifier: Programming Language :: Python :: 3.12
Requires-Python: >=3.12
License-File: LICENSE
Requires-Dist: psutil
Requires-Dist: hytils
Requires-Dist: nvidia-ml-py
Dynamic: license-file
